LICENSE.txt
MANIFEST.in
README.rst
requirements.txt
setup.py
doc/source/Makefile
doc/source/_fake_links.rst
doc/source/about.rst
doc/source/calendar_classes.rst
doc/source/compound_timeboard.png
doc/source/conf.py
doc/source/data_model.rst
doc/source/doing_calculations.rst
doc/source/exceptions.rst
doc/source/index.rst
doc/source/installation.rst
doc/source/interval_class.rst
doc/source/make.bat
doc/source/making_a_timeboard.rst
doc/source/organizing_classes.rst
doc/source/quick_start.rst
doc/source/release_notes.rst
doc/source/requirements.txt
doc/source/simple_timeboard.png
doc/source/timeboard_class.rst
doc/source/timeboard_logo.png
doc/source/use_cases.ipynb
doc/source/using_preconfigured.rst
doc/source/workshift_class.rst
timeboard/VERSION.txt
timeboard/__init__.py
timeboard/core.py
timeboard/exceptions.py
timeboard/interval.py
timeboard/timeboard.py
timeboard/utils.py
timeboard/when.py
timeboard/workshift.py
timeboard.egg-info/PKG-INFO
timeboard.egg-info/SOURCES.txt
timeboard.egg-info/dependency_links.txt
timeboard.egg-info/not-zip-safe
timeboard.egg-info/requires.txt
timeboard.egg-info/top_level.txt
timeboard/calendars/RU.py
timeboard/calendars/UK.py
timeboard/calendars/UK_new.py
timeboard/calendars/US.py
timeboard/calendars/__init__.py
timeboard/calendars/calendarbase.py
timeboard/calendars/uk_weekly_8x5.yaml
timeboard/calendars/weekly_template.py
timeboard/templates/__init__.py
timeboard/templates/base.py
timeboard/templates/constructor.py
timeboard/templates/days_weekly.py
timeboard/tests/__init__.py
timeboard/tests/test_frames.py
timeboard/tests/test_interval_methods.py
timeboard/tests/test_intervals.py
timeboard/tests/test_intervals_compound.py
timeboard/tests/test_organizers.py
timeboard/tests/test_partitioning.py
timeboard/tests/test_patterns.py
timeboard/tests/test_timeboard.py
timeboard/tests/test_utils.py
timeboard/tests/test_workshift.py
timeboard/tests/test_workshift_compound.py
timeboard/tests/calendars/__init__.py
timeboard/tests/calendars/test_calendars_generic.py
timeboard/tests/calendars/test_calendars_ru_us_uk.py