Metadata-Version: 2.1
Name: timeboard
Version: 0.2.4
Summary: Calendar calculations over business days and work shifts
Home-page: http://timeboard.readthedocs.io
Author: Maxim Mamaev
Author-email: mmamaev2@gmail.com
License: BSD 3-Clause
Keywords: business day calendar schedule calculation shift
Platform: UNKNOWN
Classifier: Development Status :: 4 - Beta
Classifier: License :: OSI Approved :: BSD License
Classifier: Operating System :: OS Independent
Classifier: Programming Language :: Python :: 2.7
Classifier: Programming Language :: Python :: 3.6
Classifier: Programming Language :: Python :: 3.7
Classifier: Programming Language :: Python :: 3.8
Classifier: Programming Language :: Python :: 3.9
Classifier: Programming Language :: Python :: 3.10
Classifier: Topic :: Office/Business :: Scheduling
License-File: LICENSE.txt
